ddl_print/__init__.py
ddl_print/apps.py
ddl_print/management/__init__.py
ddl_print/management/commands/__init__.py
ddl_print/management/commands/ddl.py
ddl_print-0.1a0.dist-info/METADATA
ddl_print-0.1a0.dist-info/WHEEL
ddl_print-0.1a0.dist-info/RECORD
