Metadata-Version: 2.1
Name: ddl-print
Version: 0.1a0
Summary: Print DDL of your models without connecting to an actual database
Author: noamtamir
Author-email: noam.tamir@gmail.com
Requires-Python: >=3.10,<4.0
Classifier: Programming Language :: Python :: 3
Classifier: Programming Language :: Python :: 3.10
Classifier: Programming Language :: Python :: 3.11
Requires-Dist: django (>=5.0.1,<6.0.0)
